hwpers-0.4.0.dist-info/METADATA
hwpers-0.4.0.dist-info/WHEEL
hwpers-0.4.0.dist-info/licenses/LICENSE
hwpers/__init__.py
hwpers/__init__.pyi
hwpers/hwpers_py.cpython-314t-aarch64-linux-gnu.so
hwpers/hwpers_py.pyi
hwpers/py.typed
hwpers-0.4.0.dist-info/RECORD
