Metadata-Version: 2.4
Name: hwpers
Version: 0.4.0
Classifier: Development Status :: 4 - Beta
Classifier: Intended Audience :: Developers
Classifier: License :: OSI Approved :: MIT License
Classifier: License :: OSI Approved :: Apache Software License
Classifier: Programming Language :: Python :: 3
Classifier: Programming Language :: Python :: 3.12
Classifier: Programming Language :: Python :: 3.13
Classifier: Programming Language :: Python :: 3.14
Classifier: Programming Language :: Rust
Classifier: Topic :: Text Processing :: General
Classifier: Topic :: Software Development :: Libraries :: Python Modules
License-File: LICENSE
Summary: Python bindings for hwpers - A library for reading and writing Korean Hangul Word Processor (HWP) files
Keywords: hwp,hangul,korean,document,parser,word-processor
Author: Indosaram
License: MIT OR Apache-2.0
Requires-Python: >=3.12
Project-URL: Homepage, https://github.com/Indosaram/hwpers-py
Project-URL: Repository, https://github.com/Indosaram/hwpers-py
Project-URL: Documentation, https://github.com/Indosaram/hwpers-py#readme
